.coveragerc
.editorconfig
.gitignore
.travis.yml
LICENSE
README.md
pyproject.toml
requirements.txt
requirements_dev.txt
setup.cfg
setup.py
.github/workflows/python-publish.yml
democritus_utility/__init__.py
democritus_utility/utility.py
democritus_utility/utility_temp_utils.py
democritus_utility.egg-info/PKG-INFO
democritus_utility.egg-info/SOURCES.txt
democritus_utility.egg-info/dependency_links.txt
democritus_utility.egg-info/requires.txt
democritus_utility.egg-info/top_level.txt
democritus_utility.egg-info/zip-safe
tests/__init__.py
tests/test_utility.py